<?xml version='1.0' encoding='UTF-8'?>
<ns0:alto xmlns:ns0="http://www.loc.gov/standards/alto/ns-v4#" xmlns:xsi="http://www.w3.org/2001/XMLSchema-instance" xsi:schemaLocation="http://www.loc.gov/standards/alto/ns-v4# http://www.loc.gov/standards/alto/v4/alto-4-2.xsd">
  <ns0:Description>
    <ns0:MeasurementUnit>pixel</ns0:MeasurementUnit>
    <ns0:sourceImageInformation>
      <ns0:fileName>Paraphrastica_1534_00000005.jpg</ns0:fileName>
      
    </ns0:sourceImageInformation>
  </ns0:Description>
  
  <ns0:Tags>
    <ns0:OtherTag ID="BT1536" LABEL="MainZone" DESCRIPTION="block type MainZone" /><ns0:OtherTag ID="BT1537" LABEL="TitlePageZone" DESCRIPTION="block type TitlePageZone" /><ns0:OtherTag ID="BT1540" LABEL="GraphicZone" DESCRIPTION="block type GraphicZone" />
    <ns0:OtherTag ID="LT583" LABEL="DefaultLine" DESCRIPTION="line type DefaultLine" /><ns0:OtherTag ID="LT584" LABEL="CustomLine" DESCRIPTION="line type CustomLine" /><ns0:OtherTag ID="LT585" LABEL="HeadingLine" DESCRIPTION="line type HeadingLine" />
  </ns0:Tags>
  
  <ns0:Layout>
    <ns0:Page WIDTH="1206" HEIGHT="1706" PHYSICAL_IMG_NR="0" ID="eSc_dummypage_">
      <ns0:PrintSpace HPOS="0" VPOS="0" WIDTH="1206" HEIGHT="1706">
        
        <ns0:TextBlock HPOS="302" VPOS="293" WIDTH="573" HEIGHT="830" ID="eSc_textblock_6f3a4616" TAGREFS="BT1536">
          <ns0:Shape><ns0:Polygon POINTS="302 293 302 1123 875 1123 875 293" /></ns0:Shape>
          
        </ns0:TextBlock>
        
        <ns0:TextBlock HPOS="124" VPOS="50" WIDTH="920" HEIGHT="1451" ID="eSc_textblock_70051594" TAGREFS="BT1540">
          <ns0:Shape><ns0:Polygon POINTS="124 50 124 1501 1044 1501 1044 50" /></ns0:Shape>
          
        </ns0:TextBlock>
        
        <ns0:TextBlock HPOS="77" VPOS="17" WIDTH="1052" HEIGHT="1454" ID="eSc_textblock_f061539f" TAGREFS="BT1537">
          <ns0:Shape><ns0:Polygon POINTS="77 17 77 1471 1129 1471 1129 17" /></ns0:Shape>
          
        </ns0:TextBlock>
        

        
      </ns0:PrintSpace>
    </ns0:Page>
  </ns0:Layout>
</ns0:alto>